fw_gear_fhir_bundle_exporter/__init__.py
fw_gear_fhir_bundle_exporter/fhir_resource_bundle.py
fw_gear_fhir_bundle_exporter/main.py
fw_gear_fhir_bundle_exporter/parser.py
fw_gear_fhir_bundle_exporter/resources/Table.L-1.Corresponding.Codes.and.Terms.for.Human.Use.csv
fw_gear_fhir_bundle_exporter/resources/hl7.CodeSystem.v3-AdministrativeGender.csv
fw_gear_fhir_bundle_exporter/resources/hl7.CodeSystem.v3-Ethnicity.csv
fw_gear_fhir_bundle_exporter/resources/hl7.CodeSystem.v3-Race.csv
fw_gear_fhir_bundle_exporter-0.1.4.dist-info/LICENSE
fw_gear_fhir_bundle_exporter-0.1.4.dist-info/METADATA
fw_gear_fhir_bundle_exporter-0.1.4.dist-info/WHEEL
fw_gear_fhir_bundle_exporter-0.1.4.dist-info/RECORD
