Metadata-Version: 2.1
Name: fw-gear-fhir-bundle-exporter
Version: 0.1.4
Summary: Export FHIR Bundles as json files 
Home-page: https://gitlab.com/flywheel-io/scientific-solutions/gears/fhir-bundle-exporter
License: MIT
Keywords: Flywheel,Gears
Author: Flywheel
Author-email: support@flywheel.io
Requires-Python: >=3.8,<4.0
Classifier: License :: OSI Approved :: MIT License
Classifier: Programming Language :: Python :: 3
Classifier: Programming Language :: Python :: 3.8
Classifier: Programming Language :: Python :: 3.9
Classifier: Programming Language :: Python :: 3.10
Classifier: Programming Language :: Python :: 3.11
Classifier: Programming Language :: Python :: 3.12
Classifier: Topic :: Scientific/Engineering
Requires-Dist: bson (>=0.5.10,<0.6.0)
Requires-Dist: deepdiff (>=6.3.1,<7.0.0)
Requires-Dist: fhir-resources (>=7.0.2,<8.0.0)
Requires-Dist: flywheel-gear-toolkit (>=0.6,<0.7)
Requires-Dist: flywheel-sdk (>=17.0.0,<18.0.0)
Requires-Dist: fw-file (>=2.3.0,<3.0.0)
Requires-Dist: pandas (>=2.0.3,<3.0.0)
Project-URL: Repository, https://gitlab.com/flywheel-io/scientific-solutions/gears/fhir-bundle-exporter
